gempaterkini/__init__.py
latestearthquake_BMKG_id-0.4.dist-info/LICENSE
latestearthquake_BMKG_id-0.4.dist-info/METADATA
latestearthquake_BMKG_id-0.4.dist-info/WHEEL
latestearthquake_BMKG_id-0.4.dist-info/top_level.txt
latestearthquake_BMKG_id-0.4.dist-info/RECORD
